embedding_adapters/__init__.py
embedding_adapters/adapter_core.py
embedding_adapters/adapter_model.py
embedding_adapters/api.py
embedding_adapters/auth.py
embedding_adapters/cli.py
embedding_adapters/loader.py
embedding_adapters/quality.py
embedding_adapters/self_supervising_agent.py
embedding_adapters/utils/__init__.py
embedding_adapters/utils/decrypt_helper.py
embedding_adapters/utils/version_helper.py
embedding_adapters-0.0.5.dist-info/licenses/LICENSE
embedding_adapters-0.0.5.dist-info/METADATA
embedding_adapters-0.0.5.dist-info/WHEEL
embedding_adapters-0.0.5.dist-info/entry_points.txt
embedding_adapters-0.0.5.dist-info/top_level.txt
embedding_adapters-0.0.5.dist-info/RECORD
