Metadata-Version: 2.4
Name: embedding-adapters
Version: 0.0.5
Summary: Universal embedding-space translation. Neural adapters that map one model's embeddings to another.
Author: Tyler Friddle
License: NCCBL
Project-URL: Homepage, https://github.com/PotentiallyARobot/EmbeddingAdapters
Project-URL: Source, https://github.com/PotentiallyARobot/EmbeddingAdapters
Requires-Python: >=3.9
License-File: LICENSE
Requires-Dist: torch<3.0,>=2.1
Requires-Dist: numpy<3.0.0,>=1.26.4
Requires-Dist: cryptography<44,>=43
Requires-Dist: huggingface_hub<2.0.0,>=0.24
Requires-Dist: transformers<5.0.0,>=4.31.0
Requires-Dist: python-dotenv>=1.0.0
Requires-Dist: requests>=2.31.0
Dynamic: license-file
